nameparser/__init__.py
nameparser/main.py
nameparser/model.py
nameparser/tokenizer.py
nameparser/vocabulary.json
nameparser/xingshi.txt
nameparser/checkpoint/cnn_20742.pt
resumename/__init__.py
resumename/main.py
resumename/model.py
resumename/tokenizer.py
resumename/vocabulary.json
resumename/xingshi.txt
resumename/checkpoint/cnn_20742.pt
resumeprofession/__init__.py
resumeprofession/main.py
resumeprofession/zhuanye.txt
resumename-1.0.4.dist-info/LICENSE
resumename-1.0.4.dist-info/METADATA
resumename-1.0.4.dist-info/WHEEL
resumename-1.0.4.dist-info/dependency_links.txt
resumename-1.0.4.dist-info/top_level.txt
resumename-1.0.4.dist-info/RECORD
